mars_dtc/__init__.py
mars_dtc/base_calendar.py
mars_dtc/darian_calendar.py
mars_dtc/mars_dtc.py
mars_dtc/pandas_ext.py
mars_dtc/plotting.py
mars_dtc/utils.py
mars_dtc-0.1.3.dist-info/licenses/LICENSE
mars_dtc-0.1.3.dist-info/METADATA
mars_dtc-0.1.3.dist-info/WHEEL
mars_dtc-0.1.3.dist-info/top_level.txt
mars_dtc-0.1.3.dist-info/RECORD
