Metadata-Version: 2.4
Name: mars-dtc
Version: 0.1.3
Summary: Integrated Martian datetime and calendar support for Python
Author: Victor De Lima
License: MIT
Project-URL: Homepage, https://www.victordelima.com/mars-dtc/
Project-URL: Repository, https://purl.org/victordelima/mars-dtc
Keywords: mars,datetime,pandas,matplotlib,astronomy
Requires-Python: >=3.9
License-File: LICENSE
Requires-Dist: numpy
Requires-Dist: pandas
Requires-Dist: matplotlib
Requires-Dist: pyyaml
Dynamic: license-file
